tmon/__init__.py
tmon/asciichart.py
tmon/cli.py
tmon/tmon.py
tmon/utils.py
tmonpy-0.4.0.dist-info/AUTHORS.rst
tmonpy-0.4.0.dist-info/LICENSE
tmonpy-0.4.0.dist-info/METADATA
tmonpy-0.4.0.dist-info/WHEEL
tmonpy-0.4.0.dist-info/entry_points.txt
tmonpy-0.4.0.dist-info/top_level.txt
tmonpy-0.4.0.dist-info/RECORD
